fasvautil/__init__.py
fasvautil/api.py
fasvautil/io.py
fasvautil/location.py
fasvautil/logging.py
fasvautil/osm.py
fasvautil/tracer.py
fasvautil/visualization.py
fasvautil-0.5.25.dist-info/METADATA
fasvautil-0.5.25.dist-info/WHEEL
fasvautil-0.5.25.dist-info/entry_points.txt
fasvautil-0.5.25.dist-info/top_level.txt
fasvautil-0.5.25.dist-info/RECORD
