Metadata-Version: 2.1
Name: fasvautil
Version: 0.5.25
Summary: Project with utility functions used with FASva
Home-page: UNKNOWN
Author: Lars Klitzke
Author-email: Lars.Klitzke@gmail.com
License: GNU GPLv3
Platform: UNKNOWN
Classifier: Programming Language :: Python :: 3
Classifier: Programming Language :: Python :: 3.5
Classifier: Programming Language :: Unix Shell
Classifier: Intended Audience :: Science/Research
Classifier: Intended Audience :: Information Technology
Classifier: Intended Audience :: Manufacturing
Classifier: Topic :: Scientific/Engineering :: Information Analysis
Requires-Dist: matplotlib
Requires-Dist: numpy
Requires-Dist: numba
Requires-Dist: pandas
Requires-Dist: tqdm
Requires-Dist: seaborn
Requires-Dist: utm
Requires-Dist: tilemapbase
Requires-Dist: overpy2
Requires-Dist: requests
Requires-Dist: fasvaorm
Requires-Dist: pygments
Requires-Dist: coloredlogs
